{
  "_fv": 79,
  "_type": "potioneffect",
  "definition": {
    "effectName": "Detarget",
    "icon": "sink_proof",
    "color": {
      "value": -1,
      "falpha": 0.0
    },
    "onAddedSound": {
      "value": ""
    },
    "isInstant": false,
    "mobEffectCategory": "NEUTRAL",
    "renderStatusInInventory": false,
    "renderStatusInHUD": false,
    "isCuredbyHoney": false,
    "modifiers": [
      {
        "attribute": {
          "value": "FOLLOW_RANGE"
        },
        "amount": -0.9,
        "operation": "ADD_MULTIPLIED_BASE"
      },
      {
        "attribute": {
          "value": "ENTITY_REACH"
        },
        "amount": -2.0,
        "operation": "ADD_VALUE"
      }
    ]
  }
}